async_data_api/__init__.py
async_data_api/data_api.py
async_data_api/examples.py
async_data_api/utils.py
async_data_api-1.0.0.dist-info/LICENSE
async_data_api-1.0.0.dist-info/WHEEL
async_data_api-1.0.0.dist-info/METADATA
async_data_api-1.0.0.dist-info/RECORD
