Metadata-Version: 2.1
Name: async-data-api
Version: 1.0.0
Summary: Async Client for PSIs REST DataApi (https://data-api.psi.ch)
Author: Niklas Laufkoetter
Author-email: niklas.laufkoetter@psi.ch
Requires-Python: >=3.8,<4.0
Classifier: Programming Language :: Python :: 3
Classifier: Programming Language :: Python :: 3.8
Classifier: Programming Language :: Python :: 3.9
Classifier: Programming Language :: Python :: 3.10
Classifier: Programming Language :: Python :: 3.11
Requires-Dist: httpx (>=0.23.1,<0.24.0)
Requires-Dist: isodate (>=0.6.1,<0.7.0)
Requires-Dist: pandas (>=1.5.2,<2.0.0)
